docs/docsource/conf.py
nova_utils/__init__.py
nova_utils/data/__init__.py
nova_utils/data/annotation.py
nova_utils/data/data.py
nova_utils/data/static.py
nova_utils/data/stream.py
nova_utils/data/file_reader/__init__.py
nova_utils/data/file_reader/video/__init__.py
nova_utils/data/file_reader/video/decord.py
nova_utils/data/file_reader/video/decord_batch.py
nova_utils/data/file_reader/video/imageio.py
nova_utils/data/file_reader/video/moviepy.py
nova_utils/data/file_reader/video/pyav.py
nova_utils/data/handler/__init__.py
nova_utils/data/handler/file_handler.py
nova_utils/data/handler/ihandler.py
nova_utils/data/handler/nova_db_handler.py
nova_utils/data/handler/request_handler.py
nova_utils/data/handler/url_handler.py
nova_utils/data/provider/__init__.py
nova_utils/data/provider/data_manager.py
nova_utils/data/provider/dataset_iterator.py
nova_utils/interfaces/__init__.py
nova_utils/interfaces/server_module.py
nova_utils/scripts/__init__.py
nova_utils/scripts/parsers.py
nova_utils/scripts/process.py
nova_utils/scripts/train.py
nova_utils/utils/__init__.py
nova_utils/utils/anno_utils.py
nova_utils/utils/cache_utils.py
nova_utils/utils/json_utils.py
nova_utils/utils/log_utils.py
nova_utils/utils/path_utils.py
nova_utils/utils/request_utils.py
nova_utils/utils/ssi_data_types.py
nova_utils/utils/ssi_xml_utils.py
nova_utils/utils/stream_utils.py
nova_utils/utils/string_utils.py
nova_utils/utils/type_definitions.py
hcai_nova_utils-1.6.8.dist-info/METADATA
hcai_nova_utils-1.6.8.dist-info/WHEEL
hcai_nova_utils-1.6.8.dist-info/entry_points.txt
hcai_nova_utils-1.6.8.dist-info/top_level.txt
hcai_nova_utils-1.6.8.dist-info/RECORD
